HW3E5/deps/xnorGate.v
`timescale 1ns/1ns

module xnorGate(
    output xy,
    input x,
    input y
);
    xnor #(5) (xy,x,y);
endmodule

HW3E1/orGate.v
`timescale 1ns/1ns

module orGate(
    output xy,
    input x,
    input y
);
    or #(5) (xy,x,y);
endmodule

HW3E4/deps/andGate.v
`timescale 1ns/1ns

module andGate(
    output xy,
    input x,
    input y
);

    and #(5) (xy,x,y);

endmodule

HW3E1/lib/notGate.v
`timescale 1ns/1ns

module notGate(xn,x);
    input x;
    output xn;

    not #(2) (xn,x);
endmodule

HW3E2/deps/xorGate.v
`timescale 1ns/1ns

module xorGate(
    output xy,
    input x,
    input y
);

    xor #(5) (xy,x,y);

endmodule

HW3E1/FullSubtractor.v
`timescale 1ns/1ns

module fullSubtractor(
    output bo,
    output s,
    input x, y, bi
);

    xorGate x1(xor_xy, x, y);
    xorGate x2(s, xor_xy, bi);
    
    notGate n1(xn, x);
    andGate a1(bo1, xn, y);
    notGate n2(xnor_xy, xor_xy);
    andGate a2(bo2, xnor_xy, bi);
    orGate  o(bo, bo1, bo2);

endmodule

HW3E1/FullSub_tb.v
`timescale 1ns/1ns

module fullSub_tb;
  wire bo, s;
  logic x, y, z;

  fullSubtractor fs(bo,s,x,y,z);


  initial begin
    $dumpfile("fullSub.vcd");
    $dumpvars;

    x = 0;
    y = 0;
    z = 0;

    repeat (2) begin
      repeat (2) begin
        repeat (2) begin
          #20ns;
          $display(x,y,z,s,bo);
          z = z + 1;
        end
        y = y + 1;
      end
      x = x + 1;
    end
    $finish();
  end
  
                
endmodule

HW3E1/fullSub.vcd
$date
	Sun Jan 05 18:35:56 2025
$end
$version
	Icarus Verilog
$end
$timescale
	1ns
$end
$scope module fullSub_tb $end
$var wire 1 ! s $end
$var wire 1 " bo $end
$var reg 1 # x $end
$var reg 1 $ y $end
$var reg 1 % z $end
$scope module fs $end
$var wire 1 % bi $end
$var wire 1 # x $end
$var wire 1 $ y $end
$var wire 1 & xor_xy $end
$var wire 1 ' xnor_xy $end
$var wire 1 ( xn $end
$var wire 1 ! s $end
$var wire 1 ) bo2 $end
$var wire 1 * bo1 $end
$var wire 1 " bo $end
$scope module a1 $end
$var wire 1 * xy $end
$var wire 1 $ y $end
$var wire 1 ( x $end
$upscope $end
$scope module a2 $end
$var wire 1 ) xy $end
$var wire 1 % y $end
$var wire 1 ' x $end
$upscope $end
$scope module n1 $end
$var wire 1 # x $end
$var wire 1 ( xn $end
$upscope $end
$scope module n2 $end
$var wire 1 ' xn $end
$var wire 1 & x $end
$upscope $end
$scope module o $end
$var wire 1 * x $end
$var wire 1 " xy $end
$var wire 1 ) y $end
$upscope $end
$scope module x1 $end
$var wire 1 # x $end
$var wire 1 & xy $end
$var wire 1 $ y $end
$upscope $end
$scope module x2 $end
$var wire 1 & x $end
$var wire 1 ! xy $end
$var wire 1 % y $end
$upscope $end
$upscope $end
$upscope $end
$scope module xnorGate $end
$var wire 1 + x $end
$var wire 1 , xy $end
$var wire 1 - y $end
$upscope $end
$enddefinitions $end
$comment Show the parameter values. $end
$dumpall
$end
#0
$dumpvars
z-
x,
z+
x*
x)
x(
x'
x&
0%
0$
0#
x"
x!
$end
#2
1(
#5
0&
0)
0*
#7
1'
#10
0!
0"
#20
1%
#25
1)
1!
#30
1"
#40
1$
0%
#45
1*
1&
0)
0!
#47
0'
#50
1!
#60
1%
#65
0!
#80
1#
0$
0%
#82
0(
#85
0*
1!
#90
0"
#100
1%
#105
0!
#120
1$
0%
#125
0&
1!
#127
1'
#130
0!
#140
1%
#145
1)
1!
#150
1"
#160
0#
0$
0%
