HW3E5/deps/xnorGate.v
`timescale 1ns/1ns

module xnorGate(
    output xy,
    input x,
    input y
);
    xnor #(5) (xy,x,y);
endmodule

HW3E1/orGate.v
`timescale 1ns/1ns

module orGate(
    output xy,
    input x,
    input y
);
    or #(5) (xy,x,y);
endmodule

HW3E4/deps/andGate.v
`timescale 1ns/1ns

module andGate(
    output xy,
    input x,
    input y
);

    and #(5) (xy,x,y);

endmodule

HW3E1/lib/notGate.v
`timescale 1ns/1ns

module notGate(xn,x);
    input x;
    output xn;

    not #(2) (xn,x);
endmodule

HW3E2/deps/xorGate.v
`timescale 1ns/1ns

module xorGate(
    output xy,
    input x,
    input y
);

    xor #(5) (xy,x,y);

endmodule

HW3E1/FullSubtractor.v
`timescale 1ns/1ns

module fullSubtractor(
    output bo,
    output s,
    input x, y, bi
);

    xorGate x1(xor_xy, x, y);
    xorGate x2(s, xor_xy, bi);
    
    notGate n1(xn, x);
    andGate a1(bo1, xn, y);
    notGate n2(xnor_xy, xor_xy);
    andGate a2(bo2, xnor_xy, bi);
    orGate  o(bo, bo1, bo2);

endmodule

HW3E1/binarySubstractor.v
`timescale 1ns/1ns

module binarySubstractor #(parameter WIDTH=1) (
  output bOut,
  output [WIDTH-1:0] sum,
  input  [WIDTH-1:0] x,
  input  [WIDTH-1:0] y
);
  wire [WIDTH-1:0] b;

  assign bOut = b[WIDTH-1];

  fullSubtractor fs(b[0],sum[0],x[0],y[0],1'b0);

  for (genvar i = 1; i < WIDTH; i = i + 1)
  begin
    fullSubtractor fs(b[i],sum[i],x[i],y[i],b[i-1]);
  end
endmodule

HW3E1/binarySubstractor_tb.v
`timescale 1ns/1ns

module binarySubstractor_tb;
  parameter N = 8;

  wire b;
  wire [N-1:0] sub;
  logic [N-1:0] x, y;

  binarySubstractor #(N) bs(b, sub, x, y);

  initial begin
    logic unsigned [N-1:0] subs, xs, ys;

    $dumpfile("binarySubstractor.vcd");
    $dumpvars;

    repeat (100) begin
      x = $urandom_range(0,2**N-1);
      y = $urandom_range(0,2**N-1);
      #60ns;
      xs = x;
      ys = y;
      subs = sub;
      $display("%d %d %d %d ** %d %d %d", x, y, sub, b, xs, ys, subs);
    end
    $finish();
  end
                
endmodule

utils/binarySubstractor.vcd
$date
	Sun Jan 05 19:33:41 2025
$end
$version
	Icarus Verilog
$end
$timescale
	1ns
$end
$scope module binarySubstractor_tb $end
$var wire 8 ! sub [7:0] $end
$var wire 1 " b $end
$var parameter 32 # N $end
$var reg 8 $ x [7:0] $end
$var reg 8 % y [7:0] $end
$scope module bs $end
$var wire 8 & x [7:0] $end
$var wire 8 ' y [7:0] $end
$var wire 8 ( sum [7:0] $end
$var wire 1 " bOut $end
$var wire 8 ) b [7:0] $end
$var parameter 32 * WIDTH $end
$scope begin genblk1[1] $end
$var parameter 2 + i $end
$scope module fs $end
$var wire 1 , bi $end
$var wire 1 - x $end
$var wire 1 . y $end
$var wire 1 / xor_xy $end
$var wire 1 0 xnor_xy $end
$var wire 1 1 xn $end
$var wire 1 2 s $end
$var wire 1 3 bo2 $end
$var wire 1 4 bo1 $end
$var wire 1 5 bo $end
$scope module a1 $end
$var wire 1 4 xy $end
$var wire 1 . y $end
$var wire 1 1 x $end
$upscope $end
$scope module a2 $end
$var wire 1 3 xy $end
$var wire 1 , y $end
$var wire 1 0 x $end
$upscope $end
$scope module n1 $end
$var wire 1 - x $end
$var wire 1 1 xn $end
$upscope $end
$scope module n2 $end
$var wire 1 0 xn $end
$var wire 1 / x $end
$upscope $end
$scope module o $end
$var wire 1 4 x $end
$var wire 1 5 xy $end
$var wire 1 3 y $end
$upscope $end
$scope module x1 $end
$var wire 1 - x $end
$var wire 1 / xy $end
$var wire 1 . y $end
$upscope $end
$scope module x2 $end
$var wire 1 / x $end
$var wire 1 2 xy $end
$var wire 1 , y $end
$upscope $end
$upscope $end
$upscope $end
$scope begin genblk1[2] $end
$var parameter 3 6 i $end
$scope module fs $end
$var wire 1 7 bi $end
$var wire 1 8 x $end
$var wire 1 9 y $end
$var wire 1 : xor_xy $end
$var wire 1 ; xnor_xy $end
$var wire 1 < xn $end
$var wire 1 = s $end
$var wire 1 > bo2 $end
$var wire 1 ? bo1 $end
$var wire 1 @ bo $end
$scope module a1 $end
$var wire 1 ? xy $end
$var wire 1 9 y $end
$var wire 1 < x $end
$upscope $end
$scope module a2 $end
$var wire 1 > xy $end
$var wire 1 7 y $end
$var wire 1 ; x $end
$upscope $end
$scope module n1 $end
$var wire 1 8 x $end
$var wire 1 < xn $end
$upscope $end
$scope module n2 $end
$var wire 1 ; xn $end
$var wire 1 : x $end
$upscope $end
$scope module o $end
$var wire 1 ? x $end
$var wire 1 @ xy $end
$var wire 1 > y $end
$upscope $end
$scope module x1 $end
$var wire 1 8 x $end
$var wire 1 : xy $end
$var wire 1 9 y $end
$upscope $end
$scope module x2 $end
$var wire 1 : x $end
$var wire 1 = xy $end
$var wire 1 7 y $end
$upscope $end
$upscope $end
$upscope $end
$scope begin genblk1[3] $end
$var parameter 3 A i $end
$scope module fs $end
$var wire 1 B bi $end
$var wire 1 C x $end
$var wire 1 D y $end
$var wire 1 E xor_xy $end
$var wire 1 F xnor_xy $end
$var wire 1 G xn $end
$var wire 1 H s $end
$var wire 1 I bo2 $end
$var wire 1 J bo1 $end
$var wire 1 K bo $end
$scope module a1 $end
$var wire 1 J xy $end
$var wire 1 D y $end
$var wire 1 G x $end
$upscope $end
$scope module a2 $end
$var wire 1 I xy $end
$var wire 1 B y $end
$var wire 1 F x $end
$upscope $end
$scope module n1 $end
$var wire 1 C x $end
$var wire 1 G xn $end
$upscope $end
$scope module n2 $end
$var wire 1 F xn $end
$var wire 1 E x $end
$upscope $end
$scope module o $end
$var wire 1 J x $end
$var wire 1 K xy $end
$var wire 1 I y $end
$upscope $end
$scope module x1 $end
$var wire 1 C x $end
$var wire 1 E xy $end
$var wire 1 D y $end
$upscope $end
$scope module x2 $end
$var wire 1 E x $end
$var wire 1 H xy $end
$var wire 1 B y $end
$upscope $end
$upscope $end
$upscope $end
$scope begin genblk1[4] $end
$var parameter 4 L i $end
$scope module fs $end
$var wire 1 M bi $end
$var wire 1 N x $end
$var wire 1 O y $end
$var wire 1 P xor_xy $end
$var wire 1 Q xnor_xy $end
$var wire 1 R xn $end
$var wire 1 S s $end
$var wire 1 T bo2 $end
$var wire 1 U bo1 $end
$var wire 1 V bo $end
$scope module a1 $end
$var wire 1 U xy $end
$var wire 1 O y $end
$var wire 1 R x $end
$upscope $end
$scope module a2 $end
$var wire 1 T xy $end
$var wire 1 M y $end
$var wire 1 Q x $end
$upscope $end
$scope module n1 $end
$var wire 1 N x $end
$var wire 1 R xn $end
$upscope $end
$scope module n2 $end
$var wire 1 Q xn $end
$var wire 1 P x $end
$upscope $end
$scope module o $end
$var wire 1 U x $end
$var wire 1 V xy $end
$var wire 1 T y $end
$upscope $end
$scope module x1 $end
$var wire 1 N x $end
$var wire 1 P xy $end
$var wire 1 O y $end
$upscope $end
$scope module x2 $end
$var wire 1 P x $end
$var wire 1 S xy $end
$var wire 1 M y $end
$upscope $end
$upscope $end
$upscope $end
$scope begin genblk1[5] $end
$var parameter 4 W i $end
$scope module fs $end
$var wire 1 X bi $end
$var wire 1 Y x $end
$var wire 1 Z y $end
$var wire 1 [ xor_xy $end
$var wire 1 \ xnor_xy $end
$var wire 1 ] xn $end
$var wire 1 ^ s $end
$var wire 1 _ bo2 $end
$var wire 1 ` bo1 $end
$var wire 1 a bo $end
$scope module a1 $end
$var wire 1 ` xy $end
$var wire 1 Z y $end
$var wire 1 ] x $end
$upscope $end
$scope module a2 $end
$var wire 1 _ xy $end
$var wire 1 X y $end
$var wire 1 \ x $end
$upscope $end
$scope module n1 $end
$var wire 1 Y x $end
$var wire 1 ] xn $end
$upscope $end
$scope module n2 $end
$var wire 1 \ xn $end
$var wire 1 [ x $end
$upscope $end
$scope module o $end
$var wire 1 ` x $end
$var wire 1 a xy $end
$var wire 1 _ y $end
$upscope $end
$scope module x1 $end
$var wire 1 Y x $end
$var wire 1 [ xy $end
$var wire 1 Z y $end
$upscope $end
$scope module x2 $end
$var wire 1 [ x $end
$var wire 1 ^ xy $end
$var wire 1 X y $end
$upscope $end
$upscope $end
$upscope $end
$scope begin genblk1[6] $end
$var parameter 4 b i $end
$scope module fs $end
$var wire 1 c bi $end
$var wire 1 d x $end
$var wire 1 e y $end
$var wire 1 f xor_xy $end
$var wire 1 g xnor_xy $end
$var wire 1 h xn $end
$var wire 1 i s $end
$var wire 1 j bo2 $end
$var wire 1 k bo1 $end
$var wire 1 l bo $end
$scope module a1 $end
$var wire 1 k xy $end
$var wire 1 e y $end
$var wire 1 h x $end
$upscope $end
$scope module a2 $end
$var wire 1 j xy $end
$var wire 1 c y $end
$var wire 1 g x $end
$upscope $end
$scope module n1 $end
$var wire 1 d x $end
$var wire 1 h xn $end
$upscope $end
$scope module n2 $end
$var wire 1 g xn $end
$var wire 1 f x $end
$upscope $end
$scope module o $end
$var wire 1 k x $end
$var wire 1 l xy $end
$var wire 1 j y $end
$upscope $end
$scope module x1 $end
$var wire 1 d x $end
$var wire 1 f xy $end
$var wire 1 e y $end
$upscope $end
$scope module x2 $end
$var wire 1 f x $end
$var wire 1 i xy $end
$var wire 1 c y $end
$upscope $end
$upscope $end
$upscope $end
$scope begin genblk1[7] $end
$var parameter 4 m i $end
$scope module fs $end
$var wire 1 n bi $end
$var wire 1 o x $end
$var wire 1 p y $end
$var wire 1 q xor_xy $end
$var wire 1 r xnor_xy $end
$var wire 1 s xn $end
$var wire 1 t s $end
$var wire 1 u bo2 $end
$var wire 1 v bo1 $end
$var wire 1 w bo $end
$scope module a1 $end
$var wire 1 v xy $end
$var wire 1 p y $end
$var wire 1 s x $end
$upscope $end
$scope module a2 $end
$var wire 1 u xy $end
$var wire 1 n y $end
$var wire 1 r x $end
$upscope $end
$scope module n1 $end
$var wire 1 o x $end
$var wire 1 s xn $end
$upscope $end
$scope module n2 $end
$var wire 1 r xn $end
$var wire 1 q x $end
$upscope $end
$scope module o $end
$var wire 1 v x $end
$var wire 1 w xy $end
$var wire 1 u y $end
$upscope $end
$scope module x1 $end
$var wire 1 o x $end
$var wire 1 q xy $end
$var wire 1 p y $end
$upscope $end
$scope module x2 $end
$var wire 1 q x $end
$var wire 1 t xy $end
$var wire 1 n y $end
$upscope $end
$upscope $end
$upscope $end
$scope module fs $end
$var wire 1 x bi $end
$var wire 1 y x $end
$var wire 1 z y $end
$var wire 1 { xor_xy $end
$var wire 1 | xnor_xy $end
$var wire 1 } xn $end
$var wire 1 ~ s $end
$var wire 1 !" bo2 $end
$var wire 1 "" bo1 $end
$var wire 1 #" bo $end
$scope module a1 $end
$var wire 1 "" xy $end
$var wire 1 z y $end
$var wire 1 } x $end
$upscope $end
$scope module a2 $end
$var wire 1 !" xy $end
$var wire 1 x y $end
$var wire 1 | x $end
$upscope $end
$scope module n1 $end
$var wire 1 y x $end
$var wire 1 } xn $end
$upscope $end
$scope module n2 $end
$var wire 1 | xn $end
$var wire 1 { x $end
$upscope $end
$scope module o $end
$var wire 1 "" x $end
$var wire 1 #" xy $end
$var wire 1 !" y $end
$upscope $end
$scope module x1 $end
$var wire 1 y x $end
$var wire 1 { xy $end
$var wire 1 z y $end
$upscope $end
$scope module x2 $end
$var wire 1 { x $end
$var wire 1 ~ xy $end
$var wire 1 x y $end
$upscope $end
$upscope $end
$upscope $end
$scope begin $unm_blk_1 $end
$var reg 8 $" subs [7:0] $end
$var reg 8 %" xs [7:0] $end
$var reg 8 &" ys [7:0] $end
$upscope $end
$upscope $end
$scope module xnorGate $end
$var wire 1 '" x $end
$var wire 1 (" xy $end
$var wire 1 )" y $end
$upscope $end
$enddefinitions $end
$comment Show the parameter values. $end
$dumpall
b111 m
b110 b
b101 W
b100 L
b11 A
b10 6
b1 +
b1000 *
b1000 #
$end
#0
$dumpvars
z)"
x("
z'"
bx &"
bx %"
bx $"
x#"
x""
x!"
x~
x}
x|
x{
0z
0y
0x
xw
xv
xu
xt
xs
xr
xq
0p
1o
xn
xl
xk
xj
xi
xh
xg
xf
1e
0d
xc
xa
x`
x_
x^
x]
x\
x[
0Z
0Y
xX
xV
xU
xT
xS
xR
xQ
xP
0O
1N
xM
xK
xJ
xI
xH
xG
xF
xE
0D
0C
xB
x@
x?
x>
x=
x<
x;
x:
09
08
x7
x5
x4
x3
x2
x1
x0
x/
0.
1-
x,
bx )
bx (
b1000000 '
b10010010 &
b1000000 %
b10010010 $
x"
bx !
$end
#2
01
1<
1G
0R
1]
1h
0s
1}
#5
04
0?
0J
0U
0`
0v
0""
1/
0:
0E
1P
0[
1f
1q
0{
0!"
#7
00
1;
1F
0Q
1\
0g
0r
1|
1k
#10
0,
bx0 !
bx0 (
0~
bx0 )
0#"
#12
1n
03
0T
0j
0u
bx1xxxxx0 )
1l
#15
bx10 !
bx10 (
12
#17
07
0X
0"
b0xxxxx10 !
b0xxxxx10 (
0t
05
0V
b1x0xx00 )
0w
#22
0>
0=
0_
b0x0xx010 !
b0x0xx010 (
0^
#27
0B
0c
0@
b100x000 )
0a
#32
0I
0H
b10x0010 !
b10x0010 (
1i
#37
0M
b1000000 )
0K
#42
b1010010 !
b1010010 (
1S
#60
1O
1Z
0e
1z
0-
18
0N
0o
b110001 %
b110001 '
b100 $
b100 &
b1010010 $"
b1000000 &"
b10010010 %"
#62
11
0<
1R
1s
#65
1`
1[
0k
0f
1""
1{
0/
1:
0q
#67
0\
1g
0|
10
0;
1r
1U
#70
1c
0n
1,
1a
1^
0l
0i
b100001 )
1#"
1~
02
1=
b10110101 !
b10110101 (
1t
#72
1X
b110001 )
1V
#75
1j
1i
0t
13
b1110111 !
b1110111 (
12
#77
b1010111 !
b1010111 (
0^
#80
1n
17
1l
b1110011 )
15
#85
1u
1t
b11010011 !
b11010011 (
0=
#90
1"
b11110011 )
1w
#120
1.
19
0O
0Z
1e
1p
0z
1-
1o
b11000110 %
b11000110 '
b10000110 $
b10000110 &
b11010011 $"
b110001 &"
b100 %"
#122
01
0s
#125
0:
0U
0P
0`
0[
1k
1f
0""
0{
#127
1;
1Q
1\
0g
1|
#130
0X
0c
0,
1=
0V
0S
0a
1^
0i
b11000010 )
0#"
b10100110 !
b10100110 (
0~
#132
1>
0j
#135
0^
1i
03
b11000100 !
b11000100 (
02
#137
1B
b11000110 )
1@
#140
07
b11000100 )
05
#142
1I
b11001100 !
b11001100 (
1H
#145
0>
b11001000 !
b11001000 (
0=
#147
1M
b11001100 )
1K
#150
0B
b11001000 )
0@
#152
1T
b11011000 !
b11011000 (
1S
#155
0I
b11010000 !
b11010000 (
0H
#157
1X
b11011000 )
1V
#160
0M
b11010000 )
0K
#162
1_
b11110000 !
b11110000 (
1^
#165
0T
b11100000 !
b11100000 (
0S
#167
1c
b11110000 )
1a
#170
0X
b11100000 )
0V
#172
b10100000 !
b10100000 (
0i
#175
0_
b10000000 !
b10000000 (
0^
#180
0c
0.
09
1D
0e
0p
1z
08
1N
1Y
0o
b11000000 )
0a
b1001 %
b1001 '
b110010 $
b110010 &
b10000000 $"
b11000110 &"
b10000110 %"
#182
1<
0R
0]
1s
#185
b11000000 !
b11000000 (
1i
1/
1J
1E
0k
0f
1""
1{
1P
1[
#187
00
0F
1g
0|
0Q
0\
#190
1M
0n
1,
12
1K
1H
0l
0i
b10001001 )
1#"
1~
1S
b10111011 !
b10111011 (
1^
#195
0S
0u
0t
b101001 !
b101001 (
02
#200
0"
b1001 )
0w
#240
1.
19
0D
1p
0z
0-
0N
0Y
1o
b10000110 %
b10000110 '
b10000000 $
b10000000 &
b101001 $"
b1001 &"
b110010 %"
#242
11
1R
1]
0s
#245
1?
1:
0J
0E
0""
0{
0P
0[
#247
0;
1F
1|
1Q
1\
14
#250
1B
0M
0,
1@
1=
0K
0H
b100 )
0#"
0~
1S
b10100 !
b10100 (
0^
#252
17
b110 )
15
#255
1I
1H
0S
b1110 !
b1110 (
12
#257
b1010 !
b1010 (
0=
#260
1M
b1110 )
1K
#265
1T
b11010 !
b11010 (
1S
#270
1X
b11110 )
1V
#275
1_
b111010 !
b111010 (
1^
#280
1c
b111110 )
1a
#285
1j
b1111010 !
b1111010 (
1i
#290
1n
b1111110 )
1l
#295
1u
b11111010 !
b11111010 (
1t
#300
1"
1D
1O
1-
1C
1N
1Y
1y
b11111110 )
1w
b10011110 %
b10011110 '
b10111011 $
b10111011 &
b11111010 $"
b10000110 &"
b10000000 %"
#302
01
0G
0R
0]
0}
#305
0/
1[
1{
#307
10
0\
0|
04
#310
02
0^
b11011001 !
b11011001 (
1~
#312
07
0_
b11111100 )
05
#317
0c
b11011101 !
b11011101 (
1=
b11011100 )
0a
#322
0j
b10011101 !
b10011101 (
0i
#327
0n
b10011100 )
0l
#332
0u
b11101 !
b11101 (
0t
#337
0"
b11100 )
0w
#360
0D
0O
1e
18
0C
1d
0y
b11000110 %
b11000110 '
b11110110 $
b11110110 &
b11101 $"
b10011110 &"
b10111011 %"
#362
0<
1G
0h
1}
#365
1P
0:
0{
#367
0Q
1;
1|
0?
#370
0S
0=
b1000 !
b1000 (
0~
#372
0B
0T
b11000 )
0@
#377
0X
0I
b0 !
b0 (
0H
b1000 )
0V
#382
0M
b100000 !
b100000 (
1^
b0 )
0K
#387
b110000 !
b110000 (
1S
#420
09
1Z
0p
1z
0-
1C
b1100011 %
b1100011 '
b11111100 $
b11111100 &
b110000 $"
b11000110 &"
b11110110 %"
#422
11
0G
#425
1:
0[
1q
1""
1{
1/
1E
#427
0;
1\
0r
0|
00
0F
14
#430
1,
1=
0^
1t
b1 )
1#"
1~
12
b10011111 !
b10011111 (
1H
#432
17
b11 )
15
#435
b10011101 !
b10011101 (
02
#437
b10011001 !
b10011001 (
0=
#480
0.
19
1O
0Z
1-
08
0C
0N
0o
b1010101 %
b1010101 '
b1100010 $
b1100010 &
b10011001 $"
b1100011 &"
b11111100 %"
#482
01
1<
1G
1R
1s
#485
04
1[
0E
0q
#487
0\
1F
1r
1?
1U
#490
07
b1 )
05
1^
0H
b110001 !
b110001 (
0t
#492
1B
1X
1@
b10101 )
1V
#495
b110101 !
b110101 (
1=
#497
1I
1H
b11101 !
b11101 (
0^
#502
1M
b11101 )
1K
#507
b1101 !
b1101 (
0S
#540
1.
09
1D
1Z
0e
1N
1o
b111011 %
b111011 '
b11110010 $
b11110010 &
b1101 $"
b1010101 &"
b1100010 %"
#542
0R
0s
#545
0/
0?
0:
1J
1E
0[
1f
0P
1q
#547
10
1;
0F
1\
0g
1Q
0r
0U
#550
0B
12
b11001 )
0@
0=
0H
1^
1i
1S
b11110011 !
b11110011 (
1t
#552
0X
13
0I
1_
1T
b1001 )
0V
#555
b11111011 !
b11111011 (
1H
#557
17
1c
1X
0_
b11011011 !
b11011011 (
0^
15
1a
b111011 )
1V
#562
0c
1>
1=
0i
1_
b10111111 !
b10111111 (
1^
b11011 )
0a
#567
1B
1c
b11111111 !
b11111111 (
1i
1@
b111111 )
1a
#572
0H
b10110111 !
b10110111 (
0i
#600
19
0D
0O
0Z
1e
1p
0-
1C
0N
0Y
0d
0o
1y
b11000111 %
b11000111 '
b1001 $
b1001 &
b10110111 $"
b111011 &"
b11110010 %"
#602
11
0G
1R
1]
1h
1s
0}
#605
1?
1:
0J
1/
0{
#607
0;
00
1|
14
1k
1v
0""
#610
0M
0=
b110111 )
0K
02
b10110000 !
b10110000 (
0~
#612
1n
1"
0,
0>
03
1l
1w
b11110110 )
0#"
#615
0T
b10100000 !
b10100000 (
0S
#617
0t
b100010 !
b100010 (
12
#620
0X
b11100110 )
0V
#625
0_
b10 !
b10 (
0^
#630
0c
b11000110 )
0a
#635
b1000010 !
b1000010 (
1i
#660
1Z
0p
1N
1Y
1d
1o
b1100111 %
b1100111 '
b11111001 $
b11111001 &
b1000010 $"
b11000111 &"
b1001 %"
#662
0R
0]
0h
0s
#665
0v
1P
0f
#667
0Q
1g
0k
#670
0"
b1000110 )
0w
1S
b10010 !
b10010 (
0i
#672
0n
b110 )
0l
#677
b10010010 !
b10010010 (
1t
#720
09
0z
18
0C
0o
0y
b1100010 %
b1100010 '
b1110100 $
b1110100 &
b10010010 $"
b1100111 &"
b11111001 %"
#722
0<
1G
1s
1}
#725
0?
0E
0q
#727
1F
1r
#730
0B
b10 )
0@
1H
b11010 !
b11010 (
0t
#735
b10010 !
b10010 (
0H
#780
19
1D
1O
0Z
1-
1C
0N
0d
1o
b1011110 %
b1011110 '
b10101110 $
b10101110 &
b10010 $"
b1100010 &"
b1110100 %"
#782
01
0G
1R
1h
0s
#785
0:
1[
0/
1f
1q
#787
1;
0\
10
0g
0r
04
1U
1k
#790
1=
1^
02
1i
b11110100 !
b11110100 (
1t
#792
07
1X
1n
1>
05
1V
b1010000 )
1l
#797
1B
0>
0=
0^
b1010000 !
b1010000 (
0t
b1010100 )
1@
#802
0B
1I
b1011000 !
b1011000 (
1H
b1010000 )
0@
#807
1M
0I
b1010000 !
b1010000 (
0H
b1011000 )
1K
#812
0M
b1000000 !
b1000000 (
0S
b1010000 )
0K
#817
b1010000 !
b1010000 (
1S
#840
09
0D
1Z
0e
0C
1N
0Y
0o
b110010 %
b110010 '
b10110 $
b10110 &
b1010000 $"
b1011110 &"
b10101110 %"
#842
1G
0R
1]
1s
#845
1:
0k
0f
0P
0q
#847
0;
1g
1Q
1r
0U
1`
#850
0n
1=
b10000 )
0l
0i
0S
b10000100 !
b10000100 (
1t
#852
0X
1c
0V
b100000 )
1a
#855
b100 !
b100 (
0t
#857
1^
1j
b1100100 !
b1100100 (
1i
#862
1n
b1100000 )
1l
#867
1u
b11100100 !
b11100100 (
1t
#872
1"
b11100000 )
1w
#900
0.
19
0O
0Z
1p
1z
0-
08
1Y
1y
b10000101 %
b10000101 '
b110001 $
b110001 &
b11100100 $"
b110010 &"
b10110 %"
#902
11
1<
0]
0}
#905
1P
0`
1v
1q
#907
0Q
0r
1?
#910
0c
1S
b11000000 )
0a
b1110100 !
b1110100 (
0t
#912
1B
0u
b11000100 )
1@
#915
0j
b110100 !
b110100 (
0i
#917
1I
b111100 !
b111100 (
1H
#920
0n
b10000100 )
0l
#922
1M
b10001100 )
1K
#925
b10111100 !
b10111100 (
1t
#927
b10101100 !
b10101100 (
0S
#960
09
1O
0z
0N
0Y
1d
0y
b10010000 %
b10010000 '
b1000000 $
b1000000 &
b10101100 $"
b10000101 &"
b110001 %"
#962
1R
1]
0h
1}
#965
0?
0:
0[
1f
#967
1;
1\
0g
1U
#970
0B
b10001000 )
0@
0=
0^
b11001000 !
b11001000 (
1i
#972
1X
b10011000 )
1V
#975
0I
b11000000 !
b11000000 (
0H
#977
1_
b11100000 !
b11100000 (
1^
#980
0M
b10010000 )
0K
#982
1c
b10110000 )
1a
#985
b11110000 !
b11110000 (
1S
#987
b10110000 !
b10110000 (
0i
#1020
1.
19
1D
0O
1e
0p
18
1N
1o
1y
b1001110 %
b1001110 '
b11010101 $
b11010101 &
b10110000 $"
b10010000 &"
b1000000 %"
#1022
0<
0R
0s
0}
#1025
14
1/
1J
1E
0U
0f
0v
1{
#1027
00
0F
1g
0|
#1030
17
1M
0X
0"
15
12
1K
1H
0V
1i
b101010 )
0w
b11111011 !
b11111011 (
1~
#1032
1j
#1035
1>
1=
0S
0_
b11001111 !
b11001111 (
0^
#1037
1n
b1101010 )
1l
#1040
1B
0c
1@
b1001110 )
0a
#1042
b1001111 !
b1001111 (
0t
#1045
0H
0j
b111 !
b111 (
0i
#1050
0n
b1110 )
0l
#1055
b10000111 !
b10000111 (
1t
#1080
0.
09
0e
1z
1-
08
1C
0N
0o
b1001 %
b1001 '
b1001011 $
b1001011 &
b10000111 $"
b1001110 &"
b11010101 %"
#1082
01
1<
0G
1R
1s
#1085
04
1f
0{
0E
0P
0q
#1087
0g
1|
1F
1Q
1r
0J
#1090
07
b1100 )
05
1i
0~
1H
1S
b1011110 !
b1011110 (
0t
#1092
0M
1I
1T
b100 )
0K
#1095
0>
b1011010 !
b1011010 (
0=
#1097
1M
1X
0T
b1001010 !
b1001010 (
0S
1K
b11100 )
1V
#1100
0B
b11000 )
0@
#1102
0X
1T
1S
1_
b1111010 !
b1111010 (
1^
b1000 )
0V
#1105
0I
b1110010 !
b1110010 (
0H
#1107
1X
1c
0_
b1010010 !
b1010010 (
0^
1V
b111000 )
1a
#1110
0M
b110000 )
0K
#1112
0c
1_
1^
b110010 !
b110010 (
0i
b10000 )
0a
#1115
0T
b100010 !
b100010 (
0S
#1117
1c
b1100010 !
b1100010 (
1i
b110000 )
1a
#1120
0X
b100000 )
0V
#1122
b100010 !
b100010 (
0i
#1125
0_
b10 !
b10 (
0^
#1130
0c
b0 )
0a
#1135
b1000010 !
b1000010 (
1i
#1140
1Z
18
0C
0d
0y
b101001 %
b101001 '
b110 $
b110 &
b1000010 $"
b1001 &"
b1001011 %"
#1142
0<
1G
1h
1}
#1145
1`
1[
1:
1E
0f
1{
#1147
0\
0;
0F
1g
0|
1J
1""
#1150
1c
b100000 )
1a
1^
1=
1H
0i
b101111 !
b101111 (
1~
#1152
1M
1,
1K
b101001 )
1#"
#1155
1j
b1101111 !
b1101111 (
1i
#1157
1T
1S
b1111101 !
b1111101 (
02
#1160
1n
b1101001 )
1l
#1162
1X
b1111001 )
1V
#1165
1u
b11111101 !
b11111101 (
1t
#1167
b11011101 !
b11011101 (
0^
#1170
1"
b11111001 )
1w
#1200
1.
1e
0z
0-
1N
1Y
1o
1y
b1101010 %
b1101010 '
b10110101 $
b10110101 &
b11011101 $"
b101001 &"
b110 %"
#1202
11
0R
0]
0s
0}
#1205
1k
1f
0""
1P
0[
1q
#1207
0g
0Q
1\
0r
14
0`
#1210
0,
0i
b11111000 )
0#"
0S
1^
b101101 !
b101101 (
0t
#1212
17
0c
0j
0T
1_
0u
15
b11011010 )
0a
#1215
b101111 !
b101111 (
12
#1217
0X
1c
0"
0=
b1101011 !
b1101011 (
1i
0V
1a
b1101010 )
0w
#1222
0_
0^
b1011 !
b1011 (
0i
#1227
0c
b1001010 )
0a
#1232
b1001011 !
b1001011 (
1i
#1260
19
0D
1O
0Z
1z
08
0N
0Y
0o
b1010111 %
b1010111 '
b1 $
b1 &
b1001011 $"
b1101010 &"
b10110101 %"
#1262
1<
1R
1]
1s
#1265
0J
0E
0{
0q
#1267
1F
1|
1r
1?
1U
#1270
0M
b1000010 )
0K
0H
0~
b11000010 !
b11000010 (
1t
#1272
1B
1X
1u
1@
b1010110 )
1V
#1275
b11010010 !
b11010010 (
1S
#1277
1"
1I
1H
1_
b11111010 !
b11111010 (
1^
b11010110 )
1w
#1282
1M
1c
1K
b11111110 )
1a
#1287
0S
b10101010 !
b10101010 (
0i
#1320
0O
1Z
1-
18
1C
1o
0y
b1100111 %
b1100111 '
b10001110 $
b10001110 &
b10101010 $"
b1010111 &"
b1 %"
#1322
01
0<
0G
0s
1}
#1325
0U
0P
1`
1[
0/
0:
1E
1q
1{
#1327
1Q
0\
10
1;
0F
0r
0|
04
0?
1""
#1330
0X
b11101110 )
0V
1S
0^
02
1=
0H
0t
b10101 !
b10101 (
1~
#1332
07
0B
1,
1T
0_
1>
0I
0u
05
0@
b11101001 )
1#"
#1335
b110101 !
b110101 (
1^
#1337
1X
1B
0M
0"
0>
0=
1H
13
b111011 !
b111011 (
12
1V
1@
0K
b1110101 )
0w
#1342
0B
17
0^
0H
0T
b11 !
b11 (
0S
0@
b1110011 )
15
#1347
0X
1H
1>
b1111 !
b1111 (
1=
b1100011 )
0V
#1352
1B
b101111 !
b101111 (
1^
b1100111 )
1@
#1357
b100111 !
b100111 (
0H
#1380
0.
0Z
0e
1p
0-
08
0C
1N
1y
b10000101 %
b10000101 '
b10010001 $
b10010001 &
b100111 $"
b1100111 &"
b10001110 %"
#1382
11
1<
1G
0R
0}
#1385
0`
0[
0k
0f
0q
1:
0E
1P
0{
#1387
1\
1g
1r
0;
1F
0Q
1|
1?
0""
#1390
0c
0n
0a
0^
b111 )
0l
1i
1t
0=
1H
1S
b11011010 !
b11011010 (
0~
#1392
0,
0>
1I
b110 )
0#"
#1395
0i
b11010 !
b11010 (
0t
#1397
1M
03
b11000 !
b11000 (
02
b1110 )
1K
#1402
07
b1000 !
b1000 (
0S
b1100 )
05
#1407
b1100 !
b1100 (
1=
#1440
1.
1D
1O
0p
0z
18
0N
1Y
1d
0o
b11110 %
b11110 '
b1100101 $
b1100101 &
b1100 $"
b10000101 &"
b10010001 %"
#1442
0<
1R
0]
0h
1s
#1445
14
1/
1J
1E
1{
0:
1[
1f
#1447
00
0F
0|
1;
0\
0g
0?
1U
#1450
17
b1110 )
15
12
0H
1~
0=
1^
b1100011 !
b1100011 (
1i
#1452
0B
1X
0I
0@
b11010 )
1V
#1455
1>
b1100111 !
b1100111 (
1=
#1457
1H
b1001111 !
b1001111 (
0^
#1460
1B
b11110 )
1@
#1465
b1000111 !
b1000111 (
0H
#1500
0.
0D
0O
1e
1p
1z
08
1C
1N
1o
b11000101 %
b11000101 '
b11111001 $
b11111001 &
b1000111 $"
b11110 &"
b1100101 %"
#1502
1<
0G
0R
0s
#1505
04
0/
0J
0U
0f
0{
1:
#1507
10
1g
1|
0;
1?
#1510
07
0M
0X
05
02
0K
b100 )
0V
0i
0~
b0 !
b0 (
0=
#1512
0>
#1515
1=
1S
b110100 !
b110100 (
1^
#1560
1D
1Z
0p
0z
0C
0N
0d
0y
b1101100 %
b1101100 '
b10100000 $
b10100000 &
b110100 $"
b11000101 &"
b11111001 %"
#1562
1G
1R
1h
1}
#1565
0[
1q
0P
1f
#1567
1\
0r
1Q
0g
1J
1k
#1570
0^
1t
0S
b11000100 !
b11000100 (
1i
